veracore_api_client/__init__.py
veracore_api_client/__version__.py
veracore_api_client/api.py
veracore_api_client/constants.py
veracore_api_client/exceptions.py
veracore_api_client-0.0.2.dist-info/LICENSE.txt
veracore_api_client-0.0.2.dist-info/METADATA
veracore_api_client-0.0.2.dist-info/WHEEL
veracore_api_client-0.0.2.dist-info/top_level.txt
veracore_api_client-0.0.2.dist-info/RECORD
