Metadata-Version: 2.1
Name: veracore-api-client
Version: 0.0.2
Summary: A simple class-based Python client for getting data                   from the VeraCore REST API
Home-page: https://github.com/veracore-api/veracore-api-client-python
Author: Eli Keimig
Author-email: ewkeimig@cyclops26.com
Maintainer: Eli Keimig
Maintainer-email: ewkeimig@cyclops26.com
License: GNU General Public License v3 or later (GPLv3+)
Keywords: python veracore oms wms veracore.com
Platform: UNKNOWN
Classifier: Development Status :: 3 - Alpha
Classifier: License :: OSI Approved :: GNU General Public License v3 or later (GPLv3+)
Classifier: Intended Audience :: Developers
Classifier: Intended Audience :: System Administrators
Classifier: Operating System :: OS Independent
Classifier: Topic :: Internet :: WWW/HTTP
Classifier: Programming Language :: Python :: 3.8
Classifier: Programming Language :: Python :: 3.9
License-File: LICENSE.txt
Requires-Dist: requests (>=2.22.0)
